pyofdm/codec.py
pyofdm/nyquistmodem.py
pyofdm-2.1.1.dist-info/LICENSE
pyofdm-2.1.1.dist-info/METADATA
pyofdm-2.1.1.dist-info/WHEEL
pyofdm-2.1.1.dist-info/top_level.txt
pyofdm-2.1.1.dist-info/RECORD
