Metadata-Version: 2.1
Name: pyofdm
Version: 2.1.1
Summary: OFDM transmitter and receiver
Home-page: https://github.com/dchutchings/py_ofdm
Author: Bernd Porr, David Hutchings
Author-email: mail@berndporr.me.uk, David.Hutchings@glasgow.ac.uk
Classifier: Intended Audience :: Developers
Classifier: License :: OSI Approved :: GNU General Public License v3 (GPLv3)
Classifier: Operating System :: OS Independent
Classifier: Programming Language :: Python :: 3
Classifier: Topic :: Utilities
License-File: LICENSE
Requires-Dist: komm
